OpenMagneticsVirtualBuilder/builder.py
OpenMagneticsVirtualBuilder/cadquery_builder.py
OpenMagneticsVirtualBuilder/freecad_builder.py
OpenMagneticsVirtualBuilder/utils.py
OpenMagneticsVirtualBuilder/templates/blank_background.svg
openmagneticsvirtualbuilder-0.6.12.dist-info/METADATA
openmagneticsvirtualbuilder-0.6.12.dist-info/WHEEL
openmagneticsvirtualbuilder-0.6.12.dist-info/licenses/LICENSE
openmagneticsvirtualbuilder-0.6.12.dist-info/RECORD
