Metadata-Version: 2.4
Name: OpenMagneticsVirtualBuilder
Version: 0.6.12
Summary: This project hold all the Python scripts needed to produce Freecad related files from any magnetic defined following MAL schemas. This files include 2D and 3D models, meshes, and technical drawings.
Project-URL: Homepage, https://openmagnetics.com
Project-URL: Repository, https://github.com/OpenMagnetics/MVB
Project-URL: Contact, https://www.linkedin.com/in/alfonso-martinez-de-la-torre/
Author-email: Alfonso Martinez <Alfonso_VII@hotmail.com>
License-Expression: MIT
License-File: LICENSE
Classifier: Development Status :: 4 - Beta
Classifier: Programming Language :: Python
Classifier: Programming Language :: Python :: 3.8
Classifier: Programming Language :: Python :: 3.9
Classifier: Programming Language :: Python :: 3.10
Classifier: Programming Language :: Python :: 3.11
Classifier: Programming Language :: Python :: 3.12
Classifier: Programming Language :: Python :: Implementation :: CPython
Classifier: Programming Language :: Python :: Implementation :: PyPy
Requires-Python: >=3.8
Requires-Dist: cadquery
Requires-Dist: numpy
Requires-Dist: pymkf
